AUTHORS.rst
CONTRIBUTING.rst
HISTORY.rst
LICENSE
MANIFEST.in
README.rst
setup.cfg
setup.py
docs/Makefile
docs/authors.rst
docs/conf.py
docs/contributing.rst
docs/history.rst
docs/index.rst
docs/installation.rst
docs/make.bat
docs/readme.rst
docs/usage.rst
nshowrss/__init__.py
nshowrss/nshowrss.py
nshowrss.egg-info/PKG-INFO
nshowrss.egg-info/SOURCES.txt
nshowrss.egg-info/dependency_links.txt
nshowrss.egg-info/entry_points.txt
nshowrss.egg-info/not-zip-safe
nshowrss.egg-info/pbr.json
nshowrss.egg-info/requires.txt
nshowrss.egg-info/top_level.txt
tests/__init__.py
tests/test_nshowrss.py