Metadata-Version: 1.1
Name: nshowrss
Version: 0.1.0
Summary: Ncurses interface for downloading showrss.info series, and keeping track of the watched / not watched episodes
Home-page: https://github.com/XayOn/nshowrss
Author: David Francos Cuartero
Author-email: me@davidfrancos.net
License: BSD
Keywords: nshowrss
Platform: UNKNOWN
Classifier: Development Status :: 2 - Pre-Alpha
Classifier: Intended Audience :: Developers
Classifier: License :: OSI Approved :: BSD License
Classifier: Natural Language :: English
Classifier: Programming Language :: Python :: 2
Classifier: Programming Language :: Python :: 2.6
Classifier: Programming Language :: Python :: 2.7
Classifier: Programming Language :: Python :: 3
Classifier: Programming Language :: Python :: 3.3
Classifier: Programming Language :: Python :: 3.4
